bcdtoexcess3.v
module bcdtoexcess3(A,B,C,D,w,x,y,z);
    input A,B,C,D;
    output w,x,y,z;
    
    assign w = A | (B & C) | (B & D);
    assign x = (~(B) & C) | (~(B) & D) | (B & ~(C) & ~(D));
    assign y = (~(C) & ~(D)) | (C & D);
    assign z = ~(D);
endmodule

module test;
reg A,B,C,D;
wire w,x,y,z;
bcdtoexcess3 b1(A,B,C,D,w,x,y,z);
initial begin
    $dumpfile("fifth.vcd");
    $dumpvars(0,test);

    $display("A \t B \t C \t D \t W \t X \t Y \t Z");
    $monitor("%b \t %b \t %b \t %b \t %b \t %b \t %b \t %b",A,B,C,D,w,x,y,z);
    A = 0;B = 0;C = 0; D = 0;
    #10;
    A = 0;B = 0;C = 0; D = 1;
    #10;
    A = 0;B = 0;C = 1; D = 0;
    #10;
    A = 0;B = 0;C = 1; D = 1;
    #10;
    A = 0;B = 1;C = 0; D = 0;
    #10;
    A = 0;B = 1;C = 0; D = 1;
    #10;
    A = 0;B = 1;C = 0; D = 0;
    #10;
    A = 0;B = 1;C = 1; D = 1;
    #10;
    A = 1;B = 0;C = 0; D = 0;
    #10;
    A = 1;B = 0;C = 0; D = 1;
    #10;
    A = 1;B = 0;C = 1; D = 0;
    #10;
    A = 1;B = 0;C = 1; D = 1;
    #10;
    A = 1;B = 1;C = 0; D = 0;
    #10;
    A = 1;B = 1;C = 0; D = 1;
    #10;
    A = 1;B = 1;C = 1; D = 0;
    #10;
    A = 1;B = 1;C = 1; D = 1;
    #10;
    $finish;
end

endmodule

fifth.vcd
$date
	Tue Nov 19 16:55:21 2024
$end
$version
	Icarus Verilog
$end
$timescale
	1s
$end
$scope module test $end
$var wire 1 ! z $end
$var wire 1 " y $end
$var wire 1 # x $end
$var wire 1 $ w $end
$var reg 1 % A $end
$var reg 1 & B $end
$var reg 1 ' C $end
$var reg 1 ( D $end
$scope module b1 $end
$var wire 1 % A $end
$var wire 1 & B $end
$var wire 1 ' C $end
$var wire 1 ( D $end
$var wire 1 $ w $end
$var wire 1 # x $end
$var wire 1 " y $end
$var wire 1 ! z $end
$upscope $end
$upscope $end
$enddefinitions $end
$comment Show the parameter values. $end
$dumpall
$end
#0
$dumpvars
0(
0'
0&
0%
0$
0#
1"
1!
$end
#10
1#
0"
0!
1(
#20
1!
0(
1'
#30
1"
0!
1(
#40
1"
1!
0(
0'
1&
#50
0#
0"
1$
0!
1(
#60
1#
1"
0$
1!
0(
#70
0#
1$
0!
1(
1'
#80
1"
1!
0(
0'
0&
1%
#90
1#
0"
0!
1(
#100
1!
0(
1'
#110
1"
0!
1(
#120
1"
1!
0(
0'
1&
#130
0#
0"
0!
1(
#140
1!
0(
1'
#150
1"
0!
1(
