demux.v
module demux(i,e,s1,s2,a,b,c,d);
input i,e,s1,s2;
output a,b,c,d;
assign a = i & e & ~(s1) & ~(s2);
assign b = i & e & ~(s1) & (s2);
assign c = i & e & (a) & ~(b);
assign d = i & e & a & b;
endmodule

module test;
reg i,e,s1,s2;
wire a,b,c,d;
demux m1(i,e,s1,s2,a,b,c,d);
initial begin
    $dumpfile("seventh.vcd");
    $dumpvars(0,test);
    $display("i \t e \t s1 \t s2 \t a \t b \t c \t d");
    $monitor("%b \t %b \t %b \t %b \t %b \t %b \t %b \t %b",i,e,s1,s2,a,b,c,d);
    i=0;e=0;s1=0;s2=0;
    #10;
    i=0;e=0;s1=0;s2=1;
    #10;
    i=0;e=0;s1=1;s2=0;
    #10;
    i=0;e=0;s1=1;s2=1;
    #10;
    i=0;e=1;s1=0;s2=0;
    #10;
    i=0;e=1;s1=0;s2=1;
    #10;
    i=0;e=1;s1=1;s2=0;
    #10;
    i=0;e=1;s1=1;s2=1;
    #10;
    i=1;e=0;s1=0;s2=0;
    #10;
    i=1;e=0;s1=0;s2=1;
    #10;
    i=1;e=0;s1=1;s2=0;
    #10;
    i=1;e=0;s1=1;s2=1;
    #10;
    i=1;e=0;s1=1;s2=1;
    #10;
    i=1;e=1;s1=0;s2=0;
    #10;
    i=1;e=1;s1=0;s2=1;
    #10;
    i=1;e=1;s1=1;s2=0;
    #10;
    i=1;e=1;s1=1;s2=1;
    #10;
    $finish;
end

endmodule

seventh.vcd
$date
	Wed Nov 20 00:12:03 2024
$end
$version
	Icarus Verilog
$end
$timescale
	1s
$end
$scope module test $end
$var wire 1 ! d $end
$var wire 1 " c $end
$var wire 1 # b $end
$var wire 1 $ a $end
$var reg 1 % e $end
$var reg 1 & i $end
$var reg 1 ' s1 $end
$var reg 1 ( s2 $end
$scope module m1 $end
$var wire 1 $ a $end
$var wire 1 # b $end
$var wire 1 " c $end
$var wire 1 ! d $end
$var wire 1 % e $end
$var wire 1 & i $end
$var wire 1 ' s1 $end
$var wire 1 ( s2 $end
$upscope $end
$upscope $end
$enddefinitions $end
$comment Show the parameter values. $end
$dumpall
$end
#0
$dumpvars
0(
0'
0&
0%
0$
0#
0"
0!
$end
#10
1(
#20
0(
1'
#30
1(
#40
0(
0'
1%
#50
1(
#60
0(
1'
#70
1(
#80
0(
0'
0%
1&
#90
1(
#100
0(
1'
#110
1(
#130
1"
1$
0(
0'
1%
#140
0"
0$
0!
1#
1(
#150
0#
0(
1'
#160
1(
