mux.v
module mux(s1,s2,a,b,c,d,y);
    input s1,s2,a,b,c,d;
    output y;
    assign y= (~(s1) & ~(s2) & a) | (~(s1) & (s2) & b) | (s1 & ~(s2) & c) + (s1 & s2 & d);
endmodule

module test;
reg s1,s2,a,b,c,d;
wire y;
mux m1(s1,s2,a,b,c,d,y);
initial begin
    $dumpfile("sixth.vcd");
    $dumpvars(0,test);
    $display("s1 \t s2 \t a \t b \t c \t d \t y");
    $monitor("%b \t %b \t %b \t %b \t %b \t %b \t %b",s1,s2,a,b,c,d,y);
    s1=0;s2=0;a=1;b=0;c=0;d=0;
    #10;
    s1=0;s2=0;a=0;b=1;c=0;d=0;
    #10;
    s1=0;s2=1;a=0;b=0;c=0;d=0;
    #10;
    s1=0;s2=1;a=0;b=1;c=0;d=0;
    #10;
    s1=1;s2=0;a=0;b=0;c=0;d=0;
    #10;
    s1=1;s2=0;a=0;b=0;c=1;d=0;
    #10;
    s1=1;s2=1;a=0;b=0;c=0;d=0;
    #10;
    s1=1;s2=1;a=0;b=0;c=0;d=1;
    #10;
    $finish;
end
endmodule

sixth.vcd
$date
	Tue Nov 19 19:57:33 2024
$end
$version
	Icarus Verilog
$end
$timescale
	1s
$end
$scope module test $end
$var wire 1 ! y $end
$var reg 1 " a $end
$var reg 1 # b $end
$var reg 1 $ c $end
$var reg 1 % d $end
$var reg 1 & s1 $end
$var reg 1 ' s2 $end
$scope module m1 $end
$var wire 1 " a $end
$var wire 1 # b $end
$var wire 1 $ c $end
$var wire 1 % d $end
$var wire 1 & s1 $end
$var wire 1 ' s2 $end
$var wire 1 ! y $end
$upscope $end
$upscope $end
$enddefinitions $end
$comment Show the parameter values. $end
$dumpall
$end
#0
$dumpvars
0'
0&
0%
0$
0#
1"
1!
$end
#10
0!
1#
0"
#20
0#
1'
#30
1!
1#
#40
0!
0#
0'
1&
#50
1!
1$
#60
0!
0$
1'
#70
1!
1%
