fulladder.v
module fulladder(A,B,C,sum,carry);
    input A,B,C;
    output sum,carry;
    assign sum = A ^ B ^ C;
    assign carry = A&B | B&C | A&C;
endmodule

module test;
    reg A,B,C;
    wire sum,carry;
    fulladder f1(A,B,C,sum,carry);
    initial begin
        $dumpfile("third.vcd");
        $dumpvars(0,test);
        
        $display("A \t B \t C \t SUM \t CARRY");
        $monitor("%b \t %b \t %b \t %b \t %b",A,B,C,sum,carry);
        A=0;B=0;C=0;
        #10;
        A=0;B=0;C=1;
        #10;
        A=0;B=1;C=0;
        #10;
        A=0;B=1;C=1;
        #10;
        A=1;B=0;C=0;
        #10;
        A=1;B=0;C=1;
        #10;
        A=1;B=1;C=0;
        #10;
        A=1;B=1;C=1;
        #10;
        $finish;
    end
endmodule

third.vcd
$date
	Tue Nov 19 03:40:52 2024
$end
$version
	Icarus Verilog
$end
$timescale
	1s
$end
$scope module test $end
$var wire 1 ! sum $end
$var wire 1 " carry $end
$var reg 1 # A $end
$var reg 1 $ B $end
$var reg 1 % C $end
$scope module f1 $end
$var wire 1 # A $end
$var wire 1 $ B $end
$var wire 1 % C $end
$var wire 1 " carry $end
$var wire 1 ! sum $end
$upscope $end
$upscope $end
$enddefinitions $end
$comment Show the parameter values. $end
$dumpall
$end
#0
$dumpvars
0%
0$
0#
0"
0!
$end
#10
1!
1%
#20
0%
1$
#30
1"
0!
1%
#40
0"
1!
0%
0$
1#
#50
1"
0!
1%
#60
0%
1$
#70
1!
1%
